hello/__init__.py
hello/hello.py
hello_test/__init__.py
hello_test/hello_test.py
testbye/__init__.py
testbye/testbye.py
testbye-0.1.dist-info/METADATA
testbye-0.1.dist-info/WHEEL
testbye-0.1.dist-info/top_level.txt
testbye-0.1.dist-info/RECORD
