Metadata-Version: 2.1
Name: testbye
Version: 0.1
Summary: your mind
Home-page: https://github.com/ab070522
Author: seongjun choi
Author-email: ab070522@gmail.com
License: UNKNOWN
Keywords: torch
Platform: UNKNOWN
Requires-Python: >=3.6
